rocket/__init__.py
rocket/file_watcher.py
rocket/logger.py
rocket/rocket.py
rocket/utils.py
tests/__init__.py
tests/conftest.py
tests/test_rocket.py
databricks_rocket-3.1.0.dist-info/LICENSE.txt
databricks_rocket-3.1.0.dist-info/METADATA
databricks_rocket-3.1.0.dist-info/WHEEL
databricks_rocket-3.1.0.dist-info/entry_points.txt
databricks_rocket-3.1.0.dist-info/top_level.txt
databricks_rocket-3.1.0.dist-info/RECORD
