Metadata-Version: 2.1
Name: databricks-rocket
Version: 3.1.0
Summary: Keep your local python scripts installed and in sync with a databricks notebook. Shortens the feedback loop to develop projects using a hybrid enviroment
Home-page: https://github.com/getyourguide/db-rocket
Author: GetYourGuide
Author-email: engineering.data-products@getyourguide.com
License: Apache 2.0
License-File: LICENSE.txt
Requires-Dist: fire
Requires-Dist: watchdog~=2.1.9
Requires-Dist: build
Requires-Dist: databricks-cli
Requires-Dist: databricks-sdk
